[{"name": "Ben Simmons", "team": "PHI", "year": "2017-18", "traditional": 12.338889212672058, "advanced": 11.51714538954914}, {"name": "Michael Carter-Williams", "team": "PHI", "year": "2013-14", "traditional": 10.164996390465665, "advanced": 4.806349438053469}, {"name": "Blake Griffin", "team": "LAC", "year": "2010-11", "traditional": 9.53232010876777, "advanced": 13.624385759404017}, {"name": "Nerlens Noel", "team": "PHI", "year": "2014-15", "traditional": 9.48511758020995, "advanced": 3.888679210046143}, {"name": "Karl-Anthony Towns", "team": "MIN", "year": "2015-16", "traditional": 9.23657064933926, "advanced": 11.310666932274062}, {"name": "Tyreke Evans", "team": "SAC", "year": "2009-10", "traditional": 8.518034593195967, "advanced": 9.112935094748236}, {"name": "Stephen Curry", "team": "GSW", "year": "2009-10", "traditional": 8.204494245079276, "advanced": 6.71646666250838}, {"name": "Luka Doncic", "team": "DAL", "year": "2018-19", "traditional": 7.910497176642101, "advanced": 9.818378393301437}, {"name": "Deandre Ayton", "team": "PHO", "year": "2018-19", "traditional": 6.979598706531253, "advanced": 6.940869182188079}, {"name": "Kristaps Porzingis", "team": "NYK", "year": "2015-16", "traditional": 6.6406565734611736, "advanced": 6.051132485145207}, {"name": "Donovan Mitchell", "team": "UTA", "year": "2017-18", "traditional": 6.1631637749121655, "advanced": 8.445796626554479}, {"name": "DeMarcus Cousins", "team": "SAC", "year": "2010-11", "traditional": 6.154945520450233, "advanced": 3.3209900712959595}, {"name": "Kyrie Irving", "team": "CLE", "year": "2011-12", "traditional": 5.852807508256112, "advanced": 9.657769273927693}, {"name": "Trae Young", "team": "ATL", "year": "2018-19", "traditional": 5.801461530907293, "advanced": 3.2317557913349724}, {"name": "Elfrid Payton", "team": "ORL", "year": "2014-15", "traditional": 5.795179690297649, "advanced": 2.214387013028872}, {"name": "Victor Oladipo", "team": "ORL", "year": "2013-14", "traditional": 5.791685866601637, "advanced": 3.14550900875743}, {"name": "Russell Westbrook", "team": "OKC", "year": "2008-09", "traditional": 5.71358126097776, "advanced": 4.793761519295984}, {"name": "Brook Lopez", "team": "NJN", "year": "2008-09", "traditional": 5.7009330431830145, "advanced": 6.0657183741750895}, {"name": "Damian Lillard", "team": "POR", "year": "2012-13", "traditional": 5.283468785417083, "advanced": 7.964206894082147}, {"name": "Brandon Jennings", "team": "MIL", "year": "2009-10", "traditional": 5.241883538460057, "advanced": 6.347656506057877}, {"name": "Mario Chalmers", "team": "MIA", "year": "2008-09", "traditional": 4.87422204704623, "advanced": 4.0547891925803565}, {"name": "Derrick Rose", "team": "CHI", "year": "2008-09", "traditional": 4.736164513049887, "advanced": 6.335307404044301}, {"name": "Marc Gasol", "team": "MEM", "year": "2008-09", "traditional": 4.638800279705814, "advanced": 6.128713982326888}, {"name": "Dennis Smith", "team": "DAL", "year": "2017-18", "traditional": 4.418967253937582, "advanced": 2.0345527568830426}, {"name": "Jaren Jackson", "team": "MEM", "year": "2018-19", "traditional": 4.360677061821596, "advanced": 4.581848383494092}, {"name": "Mitchell Robinson", "team": "NYK", "year": "2018-19", "traditional": 4.358832233714993, "advanced": 5.234967398162915}, {"name": "Emmanuel Mudiay", "team": "DEN", "year": "2015-16", "traditional": 4.323727285771436, "advanced": -1.097692058011831}, {"name": "Wendell Carter", "team": "CHI", "year": "2018-19", "traditional": 4.019275680226471, "advanced": 2.01602006713113}, {"name": "Andrew Wiggins", "team": "MIN", "year": "2014-15", "traditional": 3.991958852520349, "advanced": 3.3541313593710633}, {"name": "O.J. Mayo", "team": "MEM", "year": "2008-09", "traditional": 3.9673821948412566, "advanced": 5.493317733280262}, {"name": "Marvin Bagley", "team": "SAC", "year": "2018-19", "traditional": 3.7505100492780787, "advanced": 3.64695317788357}, {"name": "Greg Monroe", "team": "DET", "year": "2010-11", "traditional": 3.7347853672401934, "advanced": 6.047622783986386}, {"name": "Nikola Jokic", "team": "DEN", "year": "2015-16", "traditional": 3.722926612543791, "advanced": 8.262474048656594}, {"name": "John Collins", "team": "ATL", "year": "2017-18", "traditional": 3.3935725566777895, "advanced": 5.156201309525806}, {"name": "Jayson Tatum", "team": "BOS", "year": "2017-18", "traditional": 3.392900866498508, "advanced": 6.260699099680653}, {"name": "Taj Gibson", "team": "CHI", "year": "2009-10", "traditional": 3.3754589710750285, "advanced": 2.604118172908529}, {"name": "Lauri Markkanen", "team": "CHI", "year": "2017-18", "traditional": 3.3199164783725923, "advanced": 3.478100952645293}, {"name": "Darren Collison", "team": "NOH", "year": "2009-10", "traditional": 2.8765253178701546, "advanced": 3.6046051078993067}, {"name": "D'Angelo Russell", "team": "LAL", "year": "2015-16", "traditional": 2.8214495850055563, "advanced": 1.3660747128391304}, {"name": "Kyle Kuzma", "team": "LAL", "year": "2017-18", "traditional": 2.800607175545198, "advanced": 3.9851288363002624}, {"name": "Iman Shumpert", "team": "NYK", "year": "2011-12", "traditional": 2.7081130439716734, "advanced": 1.4990323759122683}, {"name": "Eric Gordon", "team": "LAC", "year": "2008-09", "traditional": 2.7049297940547983, "advanced": 5.071392920567975}, {"name": "Kemba Walker", "team": "CHA", "year": "2011-12", "traditional": 2.6879551441403104, "advanced": 2.3919598449176744}, {"name": "Chandler Parsons", "team": "HOU", "year": "2011-12", "traditional": 2.621437624590416, "advanced": 3.0653132669326073}, {"name": "Dario Saric", "team": "PHI", "year": "2016-17", "traditional": 2.5479508061047884, "advanced": 1.4240934808084769}, {"name": "Mikal Bridges", "team": "PHO", "year": "2018-19", "traditional": 2.5083164311556696, "advanced": -0.17681174725701676}, {"name": "De'Aaron Fox", "team": "SAC", "year": "2017-18", "traditional": 2.496027961625146, "advanced": -0.9253981388884074}, {"name": "Marcus Smart", "team": "BOS", "year": "2014-15", "traditional": 2.4546417340457247, "advanced": 1.2333707430131087}, {"name": "Jason Thompson", "team": "SAC", "year": "2008-09", "traditional": 2.451546408604337, "advanced": 1.4385406230181124}, {"name": "Kevin Love", "team": "MIN", "year": "2008-09", "traditional": 2.4289543507624165, "advanced": 4.7763929611576135}, {"name": "Josh Jackson", "team": "PHO", "year": "2017-18", "traditional": 2.418231537501294, "advanced": -0.5154560354104782}, {"name": "Jusuf Nurkic", "team": "DEN", "year": "2014-15", "traditional": 2.2038277706940756, "advanced": 0.7772826056908297}, {"name": "Myles Turner", "team": "IND", "year": "2015-16", "traditional": 2.1849100649950115, "advanced": 1.8163361099974729}, {"name": "Michael Kidd-Gilchrist", "team": "CHA", "year": "2012-13", "traditional": 2.1650096470994895, "advanced": 0.7101306798385415}, {"name": "Shai Gilgeous-Alexander", "team": "LAC", "year": "2018-19", "traditional": 2.1205095815452335, "advanced": 0.06905424953117607}, {"name": "Malcolm Brogdon", "team": "MIL", "year": "2016-17", "traditional": 2.0653246865582178, "advanced": 2.9997672843101952}, {"name": "Trey Burke", "team": "UTA", "year": "2013-14", "traditional": 2.054857064877594, "advanced": 1.4498680830497808}, {"name": "Landry Fields", "team": "NYK", "year": "2010-11", "traditional": 2.0252420643047078, "advanced": 3.2516908754593663}, {"name": "Jonny Flynn", "team": "MIN", "year": "2009-10", "traditional": 1.9948601338926415, "advanced": 0.688526629091078}, {"name": "Maurice Harkless", "team": "ORL", "year": "2012-13", "traditional": 1.9416333336454235, "advanced": 0.4957026685246856}, {"name": "Kawhi Leonard", "team": "SAS", "year": "2011-12", "traditional": 1.7772145075800454, "advanced": 5.055089277389572}, {"name": "Luc Mbah a Moute", "team": "MIL", "year": "2008-09", "traditional": 1.6850991314971902, "advanced": 1.4119185513524262}, {"name": "Jordan Clarkson", "team": "LAL", "year": "2014-15", "traditional": 1.6442162483608558, "advanced": 3.6197803365087893}, {"name": "Bismack Biyombo", "team": "CHA", "year": "2011-12", "traditional": 1.612898836653739, "advanced": -3.430704335208806}, {"name": "MarShon Brooks", "team": "NJN", "year": "2011-12", "traditional": 1.4954628102313674, "advanced": 1.292102241708218}, {"name": "Brandon Knight", "team": "DET", "year": "2011-12", "traditional": 1.4698911219450193, "advanced": 1.6467118313669187}, {"name": "T.J. McConnell", "team": "PHI", "year": "2015-16", "traditional": 1.4551931366803839, "advanced": -0.39170896094449636}, {"name": "Jonas Jerebko", "team": "DET", "year": "2009-10", "traditional": 1.4432928694469807, "advanced": 2.5708546109178347}, {"name": "Tristan Thompson", "team": "CLE", "year": "2011-12", "traditional": 1.3453910109795626, "advanced": -0.9690807604411891}, {"name": "Bogdan Bogdanovic", "team": "SAC", "year": "2017-18", "traditional": 1.3333314592921672, "advanced": 2.2306648989751756}, {"name": "Nikola Mirotic", "team": "CHI", "year": "2014-15", "traditional": 1.2895138316797268, "advanced": 5.534368607740811}, {"name": "Michael Beasley", "team": "MIA", "year": "2008-09", "traditional": 1.2302514762874772, "advanced": 3.5360295291855195}, {"name": "Giannis Antetokounmpo", "team": "MIL", "year": "2013-14", "traditional": 1.200011862272473, "advanced": -1.4256074180158689}, {"name": "Jrue Holiday", "team": "PHI", "year": "2009-10", "traditional": 1.1621221699116455, "advanced": -0.24302589796770976}, {"name": "Willy Hernangomez", "team": "NYK", "year": "2016-17", "traditional": 1.1579633642494196, "advanced": 3.2157259274095935}, {"name": "Marquese Chriss", "team": "PHO", "year": "2016-17", "traditional": 1.15509475608041, "advanced": 0.021401148458091157}, {"name": "Jarrett Allen", "team": "BRK", "year": "2017-18", "traditional": 1.1132320512867162, "advanced": 2.592220901871755}, {"name": "Willie Cauley-Stein", "team": "SAC", "year": "2015-16", "traditional": 1.0817999231699282, "advanced": 1.4466944875693328}, {"name": "Isaiah Thomas", "team": "SAC", "year": "2011-12", "traditional": 1.0767281230168555, "advanced": 4.504446611471007}, {"name": "Eric Bledsoe", "team": "LAC", "year": "2010-11", "traditional": 1.0704643318742595, "advanced": -1.5986480783656374}, {"name": "Tyler Zeller", "team": "CLE", "year": "2012-13", "traditional": 1.0583335644596938, "advanced": -0.6704171148939733}, {"name": "James Harden", "team": "OKC", "year": "2009-10", "traditional": 0.8905777154227303, "advanced": 3.529029302067799}, {"name": "K.J. McDaniels", "team": "TOT", "year": "2014-15", "traditional": 0.851976922228929, "advanced": -1.6176100699793674}, {"name": "Kevin Huerter", "team": "ATL", "year": "2018-19", "traditional": 0.7801460866802112, "advanced": -1.5247553070404545}, {"name": "Mo Bamba", "team": "ORL", "year": "2018-19", "traditional": 0.690754990727982, "advanced": 0.11155463132188136}, {"name": "Marcus Thornton", "team": "NOH", "year": "2009-10", "traditional": 0.5928420038602391, "advanced": 5.211927623178319}, {"name": "Collin Sexton", "team": "CLE", "year": "2018-19", "traditional": 0.5702518061713162, "advanced": -1.6916658332634777}, {"name": "Devin Booker", "team": "PHO", "year": "2015-16", "traditional": 0.5268359376200866, "advanced": 1.0758969266199903}, {"name": "Wesley Johnson", "team": "MIN", "year": "2010-11", "traditional": 0.462022256487147, "advanced": -0.7767107064112824}, {"name": "DeJuan Blair", "team": "SAS", "year": "2009-10", "traditional": 0.42212776694122767, "advanced": 3.878261308540612}, {"name": "Alexey Shved", "team": "MIN", "year": "2012-13", "traditional": 0.4131815076226537, "advanced": -0.4881034545397458}, {"name": "Brandon Ingram", "team": "LAL", "year": "2016-17", "traditional": 0.41045288895331655, "advanced": -2.6966935045113916}, {"name": "Mason Plumlee", "team": "BRK", "year": "2013-14", "traditional": 0.4009877984267981, "advanced": 4.186268226253704}, {"name": "Justise Winslow", "team": "MIA", "year": "2015-16", "traditional": 0.28971402422010467, "advanced": -0.8626679456628992}, {"name": "Zach LaVine", "team": "MIN", "year": "2014-15", "traditional": 0.21760526142239944, "advanced": -1.8135442827659245}, {"name": "Serge Ibaka", "team": "OKC", "year": "2009-10", "traditional": 0.21515161229110458, "advanced": 0.1754010147492514}, {"name": "Markieff Morris", "team": "PHO", "year": "2011-12", "traditional": 0.2133775268213579, "advanced": 0.1373691772144645}, {"name": "Bam Adebayo", "team": "MIA", "year": "2017-18", "traditional": 0.1465067945497131, "advanced": 1.9446114761948112}, {"name": "Dillon Brooks", "team": "MEM", "year": "2017-18", "traditional": 0.13497502796057848, "advanced": -0.8205390803090579}, {"name": "Klay Thompson", "team": "GSW", "year": "2011-12", "traditional": 0.06087435370827737, "advanced": 2.264343242560555}, {"name": "Ryan Kelly", "team": "LAL", "year": "2013-14", "traditional": 0.049095815084319705, "advanced": 0.18198025224848446}, {"name": "Rudy Fernandez", "team": "POR", "year": "2008-09", "traditional": 0.04016092176099495, "advanced": 5.698756432144894}, {"name": "Josh Okogie", "team": "MIN", "year": "2018-19", "traditional": 0.020310295692205937, "advanced": -2.8023995314034496}, {"name": "Kelly Olynyk", "team": "BOS", "year": "2013-14", "traditional": -0.009276957863020685, "advanced": 2.491943689340852}, {"name": "Terrence Williams", "team": "NJN", "year": "2009-10", "traditional": -0.06411594539978716, "advanced": -1.6061381300140556}, {"name": "Kevin Knox", "team": "NYK", "year": "2018-19", "traditional": -0.1141704108194071, "advanced": -3.2107541380939906}, {"name": "Omri Casspi", "team": "SAC", "year": "2009-10", "traditional": -0.15780527464906896, "advanced": 0.8949333183839656}, {"name": "Derrick Favors", "team": "TOT", "year": "2010-11", "traditional": -0.1699412157130964, "advanced": -0.05504544886588433}, {"name": "Jerami Grant", "team": "PHI", "year": "2014-15", "traditional": -0.19162783230089908, "advanced": -3.2511536829176224}, {"name": "Kyle Singler", "team": "DET", "year": "2012-13", "traditional": -0.22260813539277172, "advanced": -0.39476368522054295}, {"name": "Stanley Johnson", "team": "DET", "year": "2015-16", "traditional": -0.29732942507723326, "advanced": -1.8475980539606052}, {"name": "Larry Nance", "team": "LAL", "year": "2015-16", "traditional": -0.3028494752026279, "advanced": -1.2399297342752469}, {"name": "Darrell Arthur", "team": "MEM", "year": "2008-09", "traditional": -0.38360301911650085, "advanced": -2.117061519041818}, {"name": "Chris Singleton", "team": "WAS", "year": "2011-12", "traditional": -0.4615830421338808, "advanced": -2.9203135060164818}, {"name": "D.J. Augustin", "team": "CHA", "year": "2008-09", "traditional": -0.49962774134691634, "advanced": 4.0055649330125025}, {"name": "Isaiah Whitehead", "team": "BRK", "year": "2016-17", "traditional": -0.534833723611482, "advanced": -4.367382840453056}, {"name": "Kris Dunn", "team": "MIN", "year": "2016-17", "traditional": -0.5748250315883482, "advanced": -4.33493454547965}, {"name": "Josh Hart", "team": "LAL", "year": "2017-18", "traditional": -0.5838699731688579, "advanced": 0.33220574543599324}, {"name": "Derrick Williams", "team": "MIN", "year": "2011-12", "traditional": -0.6433834129628994, "advanced": -0.20693123351740017}, {"name": "Gorgui Dieng", "team": "MIN", "year": "2013-14", "traditional": -0.6433887255198425, "advanced": 0.5823148538093734}, {"name": "Nate Wolters", "team": "MIL", "year": "2013-14", "traditional": -0.6465765308534651, "advanced": -1.476021878084785}, {"name": "Roy Hibbert", "team": "IND", "year": "2008-09", "traditional": -0.6931324119720639, "advanced": 1.1935782630243745}, {"name": "Jamal Murray", "team": "DEN", "year": "2016-17", "traditional": -0.7015073020791978, "advanced": -0.3231694185451949}, {"name": "Tyler Ulis", "team": "PHO", "year": "2016-17", "traditional": -0.7327457896561014, "advanced": -1.74584337157185}, {"name": "Daniel Theis", "team": "BOS", "year": "2017-18", "traditional": -0.7552601661791596, "advanced": 1.901212424062034}, {"name": "Frank Ntilikina", "team": "NYK", "year": "2017-18", "traditional": -0.7838242218200391, "advanced": -4.550271532328397}, {"name": "Allonzo Trier", "team": "NYK", "year": "2018-19", "traditional": -0.8204649086327216, "advanced": -0.9228807841140412}, {"name": "Jan Vesely", "team": "WAS", "year": "2011-12", "traditional": -0.8306288478621986, "advanced": -1.6817606104117155}, {"name": "JaVale McGee", "team": "WAS", "year": "2008-09", "traditional": -0.8498607849326045, "advanced": 0.09966686835354033}, {"name": "Frank Kaminsky", "team": "CHO", "year": "2015-16", "traditional": -0.8835470571319269, "advanced": 0.40339264484091253}, {"name": "Courtney Lee", "team": "ORL", "year": "2008-09", "traditional": -0.8835991785239805, "advanced": 1.488056999959901}, {"name": "Harrison Barnes", "team": "GSW", "year": "2012-13", "traditional": -0.9304166176699347, "advanced": -0.017486576283467864}, {"name": "Evan Turner", "team": "PHI", "year": "2010-11", "traditional": -1.0035105710498105, "advanced": -0.8835094737947131}, {"name": "Miles Bridges", "team": "CHO", "year": "2018-19", "traditional": -1.01185626346375, "advanced": -1.713400909775908}, {"name": "Wesley Matthews", "team": "UTA", "year": "2009-10", "traditional": -1.0334386837224037, "advanced": 1.9040533434163553}, {"name": "Omari Spellman", "team": "ATL", "year": "2018-19", "traditional": -1.135002147509665, "advanced": -1.9057570641702788}, {"name": "Bobby Portis", "team": "CHI", "year": "2015-16", "traditional": -1.1371410133176822, "advanced": -0.7744870982882132}, {"name": "Cody Zeller", "team": "CHA", "year": "2013-14", "traditional": -1.2117864092095783, "advanced": -0.004831690173636605}, {"name": "Ivan Johnson", "team": "ATL", "year": "2011-12", "traditional": -1.2159674477112477, "advanced": -0.08948956629291899}, {"name": "Andrew Harrison", "team": "MEM", "year": "2016-17", "traditional": -1.2947677900518904, "advanced": -2.3973499471650968}, {"name": "Rodions Kurucs", "team": "BRK", "year": "2018-19", "traditional": -1.3453537608757684, "advanced": -1.6332359003829664}, {"name": "Buddy Hield", "team": "TOT", "year": "2016-17", "traditional": -1.356587634228001, "advanced": -0.23369014224041462}, {"name": "Nick Calathes", "team": "MEM", "year": "2013-14", "traditional": -1.3899592745923681, "advanced": -1.190086954263335}, {"name": "Brandon Rush", "team": "IND", "year": "2008-09", "traditional": -1.452616374633074, "advanced": -2.5823292538272256}, {"name": "Tarik Black", "team": "TOT", "year": "2014-15", "traditional": -1.5338025401789985, "advanced": -0.3612850337471356}, {"name": "Joe Ingles", "team": "UTA", "year": "2014-15", "traditional": -1.5998326994115932, "advanced": -1.8270963399506117}, {"name": "Harry Giles", "team": "SAC", "year": "2018-19", "traditional": -1.6075347864137322, "advanced": -1.1733830521399926}, {"name": "Thomas Robinson", "team": "TOT", "year": "2012-13", "traditional": -1.619568252394128, "advanced": -3.8050811610231876}, {"name": "Marreese Speights", "team": "PHI", "year": "2008-09", "traditional": -1.6481834653217398, "advanced": 2.3544791264934517}, {"name": "Taurean Waller-Prince", "team": "ATL", "year": "2016-17", "traditional": -1.658570722109527, "advanced": -2.7193205884622715}, {"name": "Rodney McGruder", "team": "MIA", "year": "2016-17", "traditional": -1.7721938764916652, "advanced": -0.9379871780154727}, {"name": "Steven Adams", "team": "OKC", "year": "2013-14", "traditional": -1.8621964887323363, "advanced": -1.787687463128083}, {"name": "Luke Kennard", "team": "DET", "year": "2017-18", "traditional": -1.8819004882846129, "advanced": -0.366752061066157}, {"name": "Domantas Sabonis", "team": "OKC", "year": "2016-17", "traditional": -1.9185609557227696, "advanced": -4.7191444051686195}, {"name": "Phil Pressey", "team": "BOS", "year": "2013-14", "traditional": -1.9692223472489006, "advanced": -5.454607171854578}, {"name": "Pablo Prigioni", "team": "NYK", "year": "2012-13", "traditional": -1.9724381147013548, "advanced": -0.7540115677170673}, {"name": "Nicolas Batum", "team": "POR", "year": "2008-09", "traditional": -1.97494773809226, "advanced": 1.2265804729489223}, {"name": "Maxi Kleber", "team": "DAL", "year": "2017-18", "traditional": -1.9814277566228373, "advanced": -0.45878335949993576}, {"name": "Al-Farouq Aminu", "team": "LAC", "year": "2010-11", "traditional": -2.0062367647231825, "advanced": -3.0757966468949034}, {"name": "DeMar DeRozan", "team": "TOR", "year": "2009-10", "traditional": -2.0276426861715473, "advanced": -0.5274230119608274}, {"name": "Ben McLemore", "team": "SAC", "year": "2013-14", "traditional": -2.0783771373190136, "advanced": -2.38016791032893}, {"name": "Hollis Thompson", "team": "PHI", "year": "2013-14", "traditional": -2.082879646182747, "advanced": -3.1101666485303063}, {"name": "Chase Budinger", "team": "HOU", "year": "2009-10", "traditional": -2.1243371395112853, "advanced": 1.1971641075856088}, {"name": "Jalen Brunson", "team": "DAL", "year": "2018-19", "traditional": -2.162989445777337, "advanced": -2.286162060812435}, {"name": "George Hill", "team": "SAS", "year": "2008-09", "traditional": -2.185537080717337, "advanced": -0.9104267446571717}, {"name": "Jerian Grant", "team": "NYK", "year": "2015-16", "traditional": -2.199108634066934, "advanced": -2.5367548833649014}, {"name": "Jae Crowder", "team": "DAL", "year": "2012-13", "traditional": -2.254020476036774, "advanced": -1.9763922700182586}, {"name": "Elie Okobo", "team": "PHO", "year": "2018-19", "traditional": -2.274328706431813, "advanced": -5.995121069774404}, {"name": "Festus Ezeli", "team": "GSW", "year": "2012-13", "traditional": -2.349396455518458, "advanced": -4.14351404458524}, {"name": "Andrew Nicholson", "team": "ORL", "year": "2012-13", "traditional": -2.4078330500359333, "advanced": -0.6229420857777718}, {"name": "Raul Neto", "team": "UTA", "year": "2015-16", "traditional": -2.4218358342769046, "advanced": -1.9344714886223842}, {"name": "Nemanja Bjelica", "team": "MIN", "year": "2015-16", "traditional": -2.4538317621095715, "advanced": -1.5710870242624106}, {"name": "Royce O'Neale", "team": "UTA", "year": "2017-18", "traditional": -2.488102279337919, "advanced": -1.582825915066083}, {"name": "Eric Maynor", "team": "TOT", "year": "2009-10", "traditional": -2.514721119623575, "advanced": -2.3283531383035276}, {"name": "Bruce Brown", "team": "DET", "year": "2018-19", "traditional": -2.5280178987104795, "advanced": -4.546468653285503}, {"name": "Kentavious Caldwell-Pope", "team": "DET", "year": "2013-14", "traditional": -2.577188150610002, "advanced": -2.660189971072488}, {"name": "OG Anunoby", "team": "TOR", "year": "2017-18", "traditional": -2.602043921090498, "advanced": -0.9665903379845215}, {"name": "Norris Cole", "team": "MIA", "year": "2011-12", "traditional": -2.613619915306204, "advanced": -3.9300033661709985}, {"name": "Chandler Hutchison", "team": "CHI", "year": "2018-19", "traditional": -2.6658457739823316, "advanced": -4.670260348997113}, {"name": "Brian Roberts", "team": "NOH", "year": "2012-13", "traditional": -2.713524628266103, "advanced": 0.27653459816886516}, {"name": "Bojan Bogdanovic", "team": "BRK", "year": "2014-15", "traditional": -2.7463354866713976, "advanced": -0.15724748785596612}, {"name": "Gary Neal", "team": "SAS", "year": "2010-11", "traditional": -2.754295953433918, "advanced": 1.5629904960189211}, {"name": "Jeff Withey", "team": "NOP", "year": "2013-14", "traditional": -2.792909288262473, "advanced": -1.612282415700512}, {"name": "JaKarr Sampson", "team": "PHI", "year": "2014-15", "traditional": -2.81893850468138, "advanced": -4.0776179937212325}, {"name": "Dante Exum", "team": "UTA", "year": "2014-15", "traditional": -2.8233834406886356, "advanced": -5.149452621365709}, {"name": "Mario Hezonja", "team": "ORL", "year": "2015-16", "traditional": -2.8435989034635654, "advanced": -3.0333166352462664}, {"name": "Tim Hardaway", "team": "NYK", "year": "2013-14", "traditional": -2.84745124252536, "advanced": 0.7718364036344337}, {"name": "Dorian Finney-Smith", "team": "DAL", "year": "2016-17", "traditional": -2.866864316362416, "advanced": -3.521463422057879}, {"name": "Justin Jackson", "team": "SAC", "year": "2017-18", "traditional": -2.8745403013987216, "advanced": -3.3383650361623305}, {"name": "Zach Collins", "team": "POR", "year": "2017-18", "traditional": -2.9095194410743304, "advanced": -4.60812826571664}, {"name": "Matthew Dellavedova", "team": "CLE", "year": "2013-14", "traditional": -2.9183146853157336, "advanced": -2.620372671725355}, {"name": "Malcolm Delaney", "team": "ATL", "year": "2016-17", "traditional": -2.9996203851352723, "advanced": -5.187618716103254}, {"name": "Sindarius Thornwell", "team": "LAC", "year": "2017-18", "traditional": -3.021280972383944, "advanced": -4.26380352449758}, {"name": "Terrence Ross", "team": "TOR", "year": "2012-13", "traditional": -3.0349551960925227, "advanced": -2.2854664912117757}, {"name": "Landry Shamet", "team": "TOT", "year": "2018-19", "traditional": -3.055397567737189, "advanced": -1.0485730119509657}, {"name": "Jaylen Brown", "team": "BOS", "year": "2016-17", "traditional": -3.094310252824102, "advanced": -2.8150083295206443}, {"name": "Jeffery Taylor", "team": "CHA", "year": "2012-13", "traditional": -3.095387154468538, "advanced": -3.048564072645272}, {"name": "Trey Lyles", "team": "UTA", "year": "2015-16", "traditional": -3.1081943162995245, "advanced": -1.50859802190485}, {"name": "Sam Young", "team": "MEM", "year": "2009-10", "traditional": -3.1197296742000846, "advanced": -1.527450344497176}, {"name": "Omer Asik", "team": "CHI", "year": "2010-11", "traditional": -3.142968928765233, "advanced": -2.310316511762748}, {"name": "Alec Burks", "team": "UTA", "year": "2011-12", "traditional": -3.1524360020933986, "advanced": -0.22626802718443884}, {"name": "Nando De Colo", "team": "SAS", "year": "2012-13", "traditional": -3.195218946714583, "advanced": -2.27329440930315}, {"name": "Timothe Luwawu-Cabarrot", "team": "PHI", "year": "2016-17", "traditional": -3.2181314183607235, "advanced": -3.779174076246107}, {"name": "James Ennis", "team": "MIA", "year": "2014-15", "traditional": -3.23337514396128, "advanced": -2.00191453894739}, {"name": "Jimmer Fredette", "team": "SAC", "year": "2011-12", "traditional": -3.242044289538931, "advanced": -2.7188779018167204}, {"name": "Draymond Green", "team": "GSW", "year": "2012-13", "traditional": -3.2573285851738514, "advanced": -5.388722266640506}, {"name": "Juan Hernangomez", "team": "DEN", "year": "2016-17", "traditional": -3.306720377018298, "advanced": -1.9477789565440988}, {"name": "Enes Kanter", "team": "UTA", "year": "2011-12", "traditional": -3.352992889336396, "advanced": -2.6238556064540774}, {"name": "Gordon Hayward", "team": "UTA", "year": "2010-11", "traditional": -3.408777172021552, "advanced": -3.036039566555508}, {"name": "Mindaugas Kuzminskas", "team": "NYK", "year": "2016-17", "traditional": -3.5306920273596667, "advanced": -1.8819381864202696}, {"name": "Wesley Iwundu", "team": "ORL", "year": "2017-18", "traditional": -3.7567276963614216, "advanced": -5.399564012101558}, {"name": "Wayne Ellington", "team": "MIN", "year": "2009-10", "traditional": -3.8763048717021733, "advanced": -3.9704851165272577}, {"name": "Patrick McCaw", "team": "GSW", "year": "2016-17", "traditional": -3.9696402509153303, "advanced": -4.023187981257263}, {"name": "Jeff Teague", "team": "ATL", "year": "2009-10", "traditional": -4.035305917537528, "advanced": -4.052645373399354}, {"name": "Will Barton", "team": "POR", "year": "2012-13", "traditional": -4.105210400706133, "advanced": -5.219596305001311}, {"name": "Alex Abrines", "team": "OKC", "year": "2016-17", "traditional": -4.110176630048214, "advanced": -2.673364255997509}, {"name": "Davis Bertans", "team": "SAS", "year": "2016-17", "traditional": -4.140091331210119, "advanced": -0.41086610084229624}, {"name": "Malik Monk", "team": "CHO", "year": "2017-18", "traditional": -4.164208729598227, "advanced": -2.7319142090575874}, {"name": "Tony Snell", "team": "CHI", "year": "2013-14", "traditional": -4.168251979170973, "advanced": -3.9308184756715248}, {"name": "Semaj Christon", "team": "OKC", "year": "2016-17", "traditional": -4.200824165814659, "advanced": -7.640282009120555}, {"name": "Roko Ukic", "team": "TOR", "year": "2008-09", "traditional": -4.278400847432794, "advanced": -4.583552041583558}, {"name": "Shelvin Mack", "team": "WAS", "year": "2011-12", "traditional": -4.282129865634198, "advanced": -3.8008957401014802}, {"name": "Hamidou Diallo", "team": "OKC", "year": "2018-19", "traditional": -4.3068333692043295, "advanced": -4.642292805194457}, {"name": "Greivis Vasquez", "team": "MEM", "year": "2010-11", "traditional": -4.402504773450113, "advanced": -4.928412683371212}, {"name": "Frank Jackson", "team": "NOP", "year": "2018-19", "traditional": -4.521713659680779, "advanced": -5.323621132532402}, {"name": "Nik Stauskas", "team": "SAC", "year": "2014-15", "traditional": -4.696007110017709, "advanced": -5.323634989202502}, {"name": "Cedi Osman", "team": "CLE", "year": "2017-18", "traditional": -4.742485870791224, "advanced": -3.981344358404185}, {"name": "DeMarre Carroll", "team": "MEM", "year": "2009-10", "traditional": -4.812756716636137, "advanced": -5.638065413397891}, {"name": "Rashad Vaughn", "team": "MIL", "year": "2015-16", "traditional": -4.862544620802019, "advanced": -8.293422847804774}, {"name": "Kelly Oubre", "team": "WAS", "year": "2015-16", "traditional": -5.107146100895061, "advanced": -5.997374586922137}, {"name": "Semi Ojeleye", "team": "BOS", "year": "2017-18", "traditional": -5.234837664873436, "advanced": -6.789892493596683}, {"name": "Terrance Ferguson", "team": "OKC", "year": "2017-18", "traditional": -5.3181783083088146, "advanced": -5.71426366591551}, {"name": "Brandon Paul", "team": "SAS", "year": "2017-18", "traditional": -5.415274381802282, "advanced": -5.97580766006102}, {"name": "Damjan Rudez", "team": "IND", "year": "2014-15", "traditional": -5.471203831314565, "advanced": -4.164639050731193}]