[{"name": "Ben Simmons", "team": "PHI", "year": "2017-18", "traditional": 12.313147343181427, "advanced": 11.524410357346127}, {"name": "Michael Carter-Williams", "team": "PHI", "year": "2013-14", "traditional": 10.142105053209084, "advanced": 4.769465490156799}, {"name": "Blake Griffin", "team": "LAC", "year": "2010-11", "traditional": 9.510381383111266, "advanced": 13.624816962791908}, {"name": "Nerlens Noel", "team": "PHI", "year": "2014-15", "traditional": 9.4655420566721, "advanced": 3.867988568987091}, {"name": "Karl-Anthony Towns", "team": "MIN", "year": "2015-16", "traditional": 9.215638984725844, "advanced": 11.309972368124608}, {"name": "Tyreke Evans", "team": "SAC", "year": "2009-10", "traditional": 8.496184025511917, "advanced": 9.094265007961212}, {"name": "Stephen Curry", "team": "GSW", "year": "2009-10", "traditional": 8.183441135875956, "advanced": 6.6950339130148775}, {"name": "Luka Doncic", "team": "DAL", "year": "2018-19", "traditional": 7.941036318123406, "advanced": 9.929001231079162}, {"name": "Deandre Ayton", "team": "PHO", "year": "2018-19", "traditional": 6.9612836306457755, "advanced": 6.925247212218829}, {"name": "Kristaps Porzingis", "team": "NYK", "year": "2015-16", "traditional": 6.622477944742952, "advanced": 6.026837967857364}, {"name": "Donovan Mitchell", "team": "UTA", "year": "2017-18", "traditional": 6.144299715900001, "advanced": 8.421447972484277}, {"name": "DeMarcus Cousins", "team": "SAC", "year": "2010-11", "traditional": 6.137327616492539, "advanced": 3.277670833802513}, {"name": "Kyrie Irving", "team": "CLE", "year": "2011-12", "traditional": 5.8332858279635165, "advanced": 9.646740489643204}, {"name": "Elfrid Payton", "team": "ORL", "year": "2014-15", "traditional": 5.776783588712481, "advanced": 2.181668187306611}, {"name": "Victor Oladipo", "team": "ORL", "year": "2013-14", "traditional": 5.773744990907563, "advanced": 3.1054748130911776}, {"name": "Russell Westbrook", "team": "OKC", "year": "2008-09", "traditional": 5.694909509131958, "advanced": 4.758473320898966}, {"name": "Brook Lopez", "team": "NJN", "year": "2008-09", "traditional": 5.683853422762742, "advanced": 6.046456744249026}, {"name": "Trae Young", "team": "ATL", "year": "2018-19", "traditional": 5.559407258333761, "advanced": 3.62046077150295}, {"name": "Damian Lillard", "team": "POR", "year": "2012-13", "traditional": 5.263725332043816, "advanced": 7.940014540509834}, {"name": "Brandon Jennings", "team": "MIL", "year": "2009-10", "traditional": 5.223275123609797, "advanced": 6.320173619074122}, {"name": "Mario Chalmers", "team": "MIA", "year": "2008-09", "traditional": 4.857426524259832, "advanced": 4.034828078783817}, {"name": "Derrick Rose", "team": "CHI", "year": "2008-09", "traditional": 4.717257766731592, "advanced": 6.306529479686748}, {"name": "Marc Gasol", "team": "MEM", "year": "2008-09", "traditional": 4.622827622526549, "advanced": 6.115684892371534}, {"name": "Dennis Smith", "team": "DAL", "year": "2017-18", "traditional": 4.401166572114481, "advanced": 1.9801892609197547}, {"name": "Jaren Jackson", "team": "MEM", "year": "2018-19", "traditional": 4.34476058842912, "advanced": 4.532577090437041}, {"name": "Mitchell Robinson", "team": "NYK", "year": "2018-19", "traditional": 4.3436483375056145, "advanced": 5.252425700376591}, {"name": "Emmanuel Mudiay", "team": "DEN", "year": "2015-16", "traditional": 4.30602779862596, "advanced": -1.1644692046023928}, {"name": "Wendell Carter", "team": "CHI", "year": "2018-19", "traditional": 4.003740951925086, "advanced": 2.0395576208318684}, {"name": "Andrew Wiggins", "team": "MIN", "year": "2014-15", "traditional": 3.975858737530778, "advanced": 3.3102028603845017}, {"name": "O.J. Mayo", "team": "MEM", "year": "2008-09", "traditional": 3.9507111798673993, "advanced": 5.456498669487562}, {"name": "Greg Monroe", "team": "DET", "year": "2010-11", "traditional": 3.72055712482087, "advanced": 6.044636032548777}, {"name": "Marvin Bagley", "team": "SAC", "year": "2018-19", "traditional": 3.71086429717416, "advanced": 3.5993151277668134}, {"name": "Nikola Jokic", "team": "DEN", "year": "2015-16", "traditional": 3.7079208192186415, "advanced": 8.271267144623108}, {"name": "John Collins", "team": "ATL", "year": "2017-18", "traditional": 3.3789166294662074, "advanced": 5.146647395868809}, {"name": "Jayson Tatum", "team": "BOS", "year": "2017-18", "traditional": 3.3779223453829865, "advanced": 6.245768362995432}, {"name": "Taj Gibson", "team": "CHI", "year": "2009-10", "traditional": 3.36113658468636, "advanced": 2.5785717048531485}, {"name": "Lauri Markkanen", "team": "CHI", "year": "2017-18", "traditional": 3.305036000057826, "advanced": 3.442058559516807}, {"name": "Darren Collison", "team": "NOH", "year": "2009-10", "traditional": 2.8601156574186777, "advanced": 3.569121735796762}, {"name": "D'Angelo Russell", "team": "LAL", "year": "2015-16", "traditional": 2.806379342673467, "advanced": 1.3195109498742088}, {"name": "Kyle Kuzma", "team": "LAL", "year": "2017-18", "traditional": 2.785749595585755, "advanced": 3.950223218903506}, {"name": "Iman Shumpert", "team": "NYK", "year": "2011-12", "traditional": 2.694173918069834, "advanced": 1.4666496201500987}, {"name": "Eric Gordon", "team": "LAC", "year": "2008-09", "traditional": 2.6896056339229903, "advanced": 5.0434364533438485}, {"name": "Kemba Walker", "team": "CHA", "year": "2011-12", "traditional": 2.6723457977657157, "advanced": 2.3499053858671335}, {"name": "Chandler Parsons", "team": "HOU", "year": "2011-12", "traditional": 2.6075823794861326, "advanced": 3.045761759404279}, {"name": "Dario Saric", "team": "PHI", "year": "2016-17", "traditional": 2.5335603490867986, "advanced": 1.3774324188335243}, {"name": "Mikal Bridges", "team": "PHO", "year": "2018-19", "traditional": 2.4948951376154302, "advanced": -0.20574940561725907}, {"name": "De'Aaron Fox", "team": "SAC", "year": "2017-18", "traditional": 2.4806524781732224, "advanced": -0.9857945978626454}, {"name": "Marcus Smart", "team": "BOS", "year": "2014-15", "traditional": 2.440771414185107, "advanced": 1.2090492894073854}, {"name": "Jason Thompson", "team": "SAC", "year": "2008-09", "traditional": 2.437907063431458, "advanced": 1.3981367767042534}, {"name": "Kevin Love", "team": "MIN", "year": "2008-09", "traditional": 2.415432701913701, "advanced": 4.752474766104332}, {"name": "Josh Jackson", "team": "PHO", "year": "2017-18", "traditional": 2.4042930054594573, "advanced": -0.5763842292265449}, {"name": "Jusuf Nurkic", "team": "DEN", "year": "2014-15", "traditional": 2.1909255053001053, "advanced": 0.7453587996929285}, {"name": "Myles Turner", "team": "IND", "year": "2015-16", "traditional": 2.1712469658241926, "advanced": 1.780025265848942}, {"name": "Michael Kidd-Gilchrist", "team": "CHA", "year": "2012-13", "traditional": 2.1515199660688133, "advanced": 0.6721240248242285}, {"name": "Shai Gilgeous-Alexander", "team": "LAC", "year": "2018-19", "traditional": 2.1307894771432823, "advanced": 0.224489758690317}, {"name": "Malcolm Brogdon", "team": "MIL", "year": "2016-17", "traditional": 2.0506937322962884, "advanced": 2.9734846884000725}, {"name": "Trey Burke", "team": "UTA", "year": "2013-14", "traditional": 2.0388999455879775, "advanced": 1.402434760071427}, {"name": "Landry Fields", "team": "NYK", "year": "2010-11", "traditional": 2.012101890611211, "advanced": 3.2335855738513195}, {"name": "Jonny Flynn", "team": "MIN", "year": "2009-10", "traditional": 1.979783638838228, "advanced": 0.6342320118810004}, {"name": "Maurice Harkless", "team": "ORL", "year": "2012-13", "traditional": 1.9290875056890755, "advanced": 0.46299619551613935}, {"name": "Kawhi Leonard", "team": "SAS", "year": "2011-12", "traditional": 1.7649195162542703, "advanced": 5.057063362743718}, {"name": "Luc Mbah a Moute", "team": "MIL", "year": "2008-09", "traditional": 1.6728632623048276, "advanced": 1.3884610149816945}, {"name": "Jordan Clarkson", "team": "LAL", "year": "2014-15", "traditional": 1.6300136614428757, "advanced": 3.590178820071839}, {"name": "Bismack Biyombo", "team": "CHA", "year": "2011-12", "traditional": 1.600288679394199, "advanced": -3.478815472419255}, {"name": "MarShon Brooks", "team": "NJN", "year": "2011-12", "traditional": 1.4819127161917383, "advanced": 1.244561871527051}, {"name": "Brandon Knight", "team": "DET", "year": "2011-12", "traditional": 1.455453669872729, "advanced": 1.601601892923366}, {"name": "T.J. McConnell", "team": "PHI", "year": "2015-16", "traditional": 1.4415486160662856, "advanced": -0.4272791808388426}, {"name": "Jonas Jerebko", "team": "DET", "year": "2009-10", "traditional": 1.4312084066688118, "advanced": 2.5470218636385447}, {"name": "Tristan Thompson", "team": "CLE", "year": "2011-12", "traditional": 1.3331079472836667, "advanced": -1.018809490311485}, {"name": "Bogdan Bogdanovic", "team": "SAC", "year": "2017-18", "traditional": 1.319489402226366, "advanced": 2.197090289840438}, {"name": "Nikola Mirotic", "team": "CHI", "year": "2014-15", "traditional": 1.2768052036596629, "advanced": 5.52001459372532}, {"name": "Michael Beasley", "team": "MIA", "year": "2008-09", "traditional": 1.2172526307346112, "advanced": 3.488768464553462}, {"name": "Giannis Antetokounmpo", "team": "MIL", "year": "2013-14", "traditional": 1.1874078350699782, "advanced": -1.4651911874018468}, {"name": "Jrue Holiday", "team": "PHI", "year": "2009-10", "traditional": 1.14872398109015, "advanced": -0.2832527394372282}, {"name": "Willy Hernangomez", "team": "NYK", "year": "2016-17", "traditional": 1.1457350523392862, "advanced": 3.195146737567274}, {"name": "Marquese Chriss", "team": "PHO", "year": "2016-17", "traditional": 1.1428053876624924, "advanced": -0.017168709541196925}, {"name": "Jarrett Allen", "team": "BRK", "year": "2017-18", "traditional": 1.1008189003039108, "advanced": 2.574969335979144}, {"name": "Willie Cauley-Stein", "team": "SAC", "year": "2015-16", "traditional": 1.0698682836102957, "advanced": 1.4301077624619272}, {"name": "Isaiah Thomas", "team": "SAC", "year": "2011-12", "traditional": 1.0626877141228246, "advanced": 4.48515312732101}, {"name": "Eric Bledsoe", "team": "LAC", "year": "2010-11", "traditional": 1.0573773677640224, "advanced": -1.6426778516144}, {"name": "Tyler Zeller", "team": "CLE", "year": "2012-13", "traditional": 1.0459537374774062, "advanced": -0.71120849262816}, {"name": "James Harden", "team": "OKC", "year": "2009-10", "traditional": 0.8782223160499962, "advanced": 3.5080111929279516}, {"name": "K.J. McDaniels", "team": "TOT", "year": "2014-15", "traditional": 0.8396267126368402, "advanced": -1.6650336229781102}, {"name": "Kevin Huerter", "team": "ATL", "year": "2018-19", "traditional": 0.8193632720219657, "advanced": -1.5811734181139614}, {"name": "Mo Bamba", "team": "ORL", "year": "2018-19", "traditional": 0.6787191102475292, "advanced": 0.0838740687095876}, {"name": "Marcus Thornton", "team": "NOH", "year": "2009-10", "traditional": 0.5801313716621699, "advanced": 5.183977462178159}, {"name": "Collin Sexton", "team": "CLE", "year": "2018-19", "traditional": 0.5568051656529363, "advanced": -1.7648346405259348}, {"name": "Devin Booker", "team": "PHO", "year": "2015-16", "traditional": 0.51355556699509, "advanced": 1.0271761610886565}, {"name": "Wesley Johnson", "team": "MIN", "year": "2010-11", "traditional": 0.44966602842595305, "advanced": -0.8175940816384364}, {"name": "DeJuan Blair", "team": "SAS", "year": "2009-10", "traditional": 0.41079433492318057, "advanced": 3.861183743304618}, {"name": "Alexey Shved", "team": "MIN", "year": "2012-13", "traditional": 0.40005784941357864, "advanced": -0.5334987803775624}, {"name": "Brandon Ingram", "team": "LAL", "year": "2016-17", "traditional": 0.39808680518175005, "advanced": -2.7525209034771962}, {"name": "Mason Plumlee", "team": "BRK", "year": "2013-14", "traditional": 0.38945540538269763, "advanced": 4.180730593267395}, {"name": "Justise Winslow", "team": "MIA", "year": "2015-16", "traditional": 0.2784774197534144, "advanced": -0.8963613313528147}, {"name": "Zach LaVine", "team": "MIN", "year": "2014-15", "traditional": 0.2046843532474505, "advanced": -1.8728269456189601}, {"name": "Serge Ibaka", "team": "OKC", "year": "2009-10", "traditional": 0.20394644105674065, "advanced": 0.14400978900636185}, {"name": "Markieff Morris", "team": "PHO", "year": "2011-12", "traditional": 0.20199663785333183, "advanced": 0.10193730549355645}, {"name": "Bam Adebayo", "team": "MIA", "year": "2017-18", "traditional": 0.13498674155890544, "advanced": 1.9255576074856138}, {"name": "Dillon Brooks", "team": "MEM", "year": "2017-18", "traditional": 0.12315376061788175, "advanced": -0.8700681005945771}, {"name": "Klay Thompson", "team": "GSW", "year": "2011-12", "traditional": 0.04851443086324059, "advanced": 2.223141712798687}, {"name": "Ryan Kelly", "team": "LAL", "year": "2013-14", "traditional": 0.037258354748836986, "advanced": 0.15303336684189361}, {"name": "Josh Okogie", "team": "MIN", "year": "2018-19", "traditional": 0.03373719635044424, "advanced": -2.641566576616254}, {"name": "Rudy Fernandez", "team": "POR", "year": "2008-09", "traditional": 0.028256562804506946, "advanced": 5.692492626797657}, {"name": "Kelly Olynyk", "team": "BOS", "year": "2013-14", "traditional": -0.020869240473831888, "advanced": 2.46709847877805}, {"name": "Terrence Williams", "team": "NJN", "year": "2009-10", "traditional": -0.07616305156883141, "advanced": -1.6609052219406097}, {"name": "Kevin Knox", "team": "NYK", "year": "2018-19", "traditional": -0.12584758402253454, "advanced": -3.2840376377516987}, {"name": "Omri Casspi", "team": "SAC", "year": "2009-10", "traditional": -0.16910148550210813, "advanced": 0.8560457887559284}, {"name": "Derrick Favors", "team": "TOT", "year": "2010-11", "traditional": -0.1808611783789682, "advanced": -0.0894513138956505}, {"name": "Jerami Grant", "team": "PHI", "year": "2014-15", "traditional": -0.20292235163788175, "advanced": -3.3013617394436032}, {"name": "Kyle Singler", "team": "DET", "year": "2012-13", "traditional": -0.23367626138153802, "advanced": -0.43469110543232325}, {"name": "Stanley Johnson", "team": "DET", "year": "2015-16", "traditional": -0.3084100693646175, "advanced": -1.8973249177015028}, {"name": "Larry Nance", "team": "LAL", "year": "2015-16", "traditional": -0.31311141664150177, "advanced": -1.2701008505945164}, {"name": "Darrell Arthur", "team": "MEM", "year": "2008-09", "traditional": -0.39403277446557106, "advanced": -2.160388773972907}, {"name": "Chris Singleton", "team": "WAS", "year": "2011-12", "traditional": -0.47163217403584623, "advanced": -2.9557957783349367}, {"name": "D.J. Augustin", "team": "CHA", "year": "2008-09", "traditional": -0.5121772718933597, "advanced": 3.978790260704342}, {"name": "Isaiah Whitehead", "team": "BRK", "year": "2016-17", "traditional": -0.5465169530176801, "advanced": -4.429713550045678}, {"name": "Kris Dunn", "team": "MIN", "year": "2016-17", "traditional": -0.5857249535209383, "advanced": -4.379627668536224}, {"name": "Josh Hart", "team": "LAL", "year": "2017-18", "traditional": -0.5946277113182016, "advanced": 0.30723248217048393}, {"name": "Gorgui Dieng", "team": "MIN", "year": "2013-14", "traditional": -0.653684602833316, "advanced": 0.5627082212481835}, {"name": "Derrick Williams", "team": "MIN", "year": "2011-12", "traditional": -0.6540041157409281, "advanced": -0.2518058352325979}, {"name": "Nate Wolters", "team": "MIL", "year": "2013-14", "traditional": -0.6583588277665888, "advanced": -1.5209556608836488}, {"name": "Roy Hibbert", "team": "IND", "year": "2008-09", "traditional": -0.7040201635529073, "advanced": 1.1600416207204383}, {"name": "Jamal Murray", "team": "DEN", "year": "2016-17", "traditional": -0.7129973077739735, "advanced": -0.36883381020480754}, {"name": "Tyler Ulis", "team": "PHO", "year": "2016-17", "traditional": -0.7445935006879647, "advanced": -1.7957173700168696}, {"name": "Daniel Theis", "team": "BOS", "year": "2017-18", "traditional": -0.7656752740330232, "advanced": 1.8924118008481763}, {"name": "Frank Ntilikina", "team": "NYK", "year": "2017-18", "traditional": -0.7951912873543039, "advanced": -4.608287359433273}, {"name": "Allonzo Trier", "team": "NYK", "year": "2018-19", "traditional": -0.8318282473979903, "advanced": -0.9720732382702977}, {"name": "Omari Spellman", "team": "ATL", "year": "2018-19", "traditional": -0.8405524264213899, "advanced": -1.7670836355669124}, {"name": "Jan Vesely", "team": "WAS", "year": "2011-12", "traditional": -0.8406426018281021, "advanced": -1.7100596005021873}, {"name": "JaVale McGee", "team": "WAS", "year": "2008-09", "traditional": -0.8602024446219905, "advanced": 0.06125795687347302}, {"name": "Courtney Lee", "team": "ORL", "year": "2008-09", "traditional": -0.8940242254589414, "advanced": 1.4640031712579944}, {"name": "Frank Kaminsky", "team": "CHO", "year": "2015-16", "traditional": -0.8941601744043834, "advanced": 0.37174564142893285}, {"name": "Harrison Barnes", "team": "GSW", "year": "2012-13", "traditional": -0.9410069252787565, "advanced": -0.05818762077286646}, {"name": "Evan Turner", "team": "PHI", "year": "2010-11", "traditional": -1.0142267293765248, "advanced": -0.9245025885836371}, {"name": "Miles Bridges", "team": "CHO", "year": "2018-19", "traditional": -1.0221140859617603, "advanced": -1.681376519839912}, {"name": "Wesley Matthews", "team": "UTA", "year": "2009-10", "traditional": -1.0441316515432404, "advanced": 1.8787528294611864}, {"name": "Bobby Portis", "team": "CHI", "year": "2015-16", "traditional": -1.147191501840918, "advanced": -0.8190399237036048}, {"name": "Cody Zeller", "team": "CHA", "year": "2013-14", "traditional": -1.221870686231573, "advanced": -0.03821898556040346}, {"name": "Ivan Johnson", "team": "ATL", "year": "2011-12", "traditional": -1.2255935656690973, "advanced": -0.12509800936690313}, {"name": "Andrew Harrison", "team": "MEM", "year": "2016-17", "traditional": -1.3056209432914254, "advanced": -2.441351963502397}, {"name": "Rodions Kurucs", "team": "BRK", "year": "2018-19", "traditional": -1.3553873508784526, "advanced": -1.4627181115423438}, {"name": "Buddy Hield", "team": "TOT", "year": "2016-17", "traditional": -1.3672129363596315, "advanced": -0.27995352260225725}, {"name": "Nick Calathes", "team": "MEM", "year": "2013-14", "traditional": -1.4004569162430782, "advanced": -1.2246637812980987}, {"name": "Brandon Rush", "team": "IND", "year": "2008-09", "traditional": -1.4627311778830727, "advanced": -2.6322360721236135}, {"name": "Tarik Black", "team": "TOT", "year": "2014-15", "traditional": -1.5433712902554197, "advanced": -0.38957625946294505}, {"name": "Joe Ingles", "team": "UTA", "year": "2014-15", "traditional": -1.6098292011176842, "advanced": -1.8597042142049784}, {"name": "Thomas Robinson", "team": "TOT", "year": "2012-13", "traditional": -1.628833398687667, "advanced": -3.859657693452229}, {"name": "Marreese Speights", "team": "PHI", "year": "2008-09", "traditional": -1.6579842783630854, "advanced": 2.325619215769353}, {"name": "Taurean Waller-Prince", "team": "ATL", "year": "2016-17", "traditional": -1.6681285415103233, "advanced": -2.7624743973256756}, {"name": "Rodney McGruder", "team": "MIA", "year": "2016-17", "traditional": -1.7819906407246338, "advanced": -0.9684068180499574}, {"name": "Harry Giles", "team": "SAC", "year": "2018-19", "traditional": -1.7867205092768292, "advanced": -0.8617586435884852}, {"name": "Steven Adams", "team": "OKC", "year": "2013-14", "traditional": -1.8711857298082215, "advanced": -1.8102901748478666}, {"name": "Luke Kennard", "team": "DET", "year": "2017-18", "traditional": -1.891865460006716, "advanced": -0.4014209337273675}, {"name": "Domantas Sabonis", "team": "OKC", "year": "2016-17", "traditional": -1.9279837899212922, "advanced": -4.776098911961515}, {"name": "Phil Pressey", "team": "BOS", "year": "2013-14", "traditional": -1.9791621835915258, "advanced": -5.507174902495493}, {"name": "Pablo Prigioni", "team": "NYK", "year": "2012-13", "traditional": -1.9822841198102792, "advanced": -0.7728824536915296}, {"name": "Nicolas Batum", "team": "POR", "year": "2008-09", "traditional": -1.9842508612203806, "advanced": 1.214417333145328}, {"name": "Maxi Kleber", "team": "DAL", "year": "2017-18", "traditional": -1.9907975341947548, "advanced": -0.48124730980899155}, {"name": "Al-Farouq Aminu", "team": "LAC", "year": "2010-11", "traditional": -2.015251798684695, "advanced": -3.1232408218759}, {"name": "DeMar DeRozan", "team": "TOR", "year": "2009-10", "traditional": -2.0370478890823245, "advanced": -0.5686079999481944}, {"name": "Ben McLemore", "team": "SAC", "year": "2013-14", "traditional": -2.0879786965649334, "advanced": -2.431867793588675}, {"name": "Hollis Thompson", "team": "PHI", "year": "2013-14", "traditional": -2.091945755495239, "advanced": -3.1515505398378347}, {"name": "Jalen Brunson", "team": "DAL", "year": "2018-19", "traditional": -2.099762017138561, "advanced": -1.7776700561303223}, {"name": "Chase Budinger", "team": "HOU", "year": "2009-10", "traditional": -2.1339653113611012, "advanced": 1.165920856633584}, {"name": "George Hill", "team": "SAS", "year": "2008-09", "traditional": -2.1951288583935686, "advanced": -0.9489869456029323}, {"name": "Jerian Grant", "team": "NYK", "year": "2015-16", "traditional": -2.208805650887428, "advanced": -2.5847642879369643}, {"name": "Jae Crowder", "team": "DAL", "year": "2012-13", "traditional": -2.2629732177187654, "advanced": -2.0093502965287104}, {"name": "Festus Ezeli", "team": "GSW", "year": "2012-13", "traditional": -2.3579680883350327, "advanced": -4.177503347776842}, {"name": "Andrew Nicholson", "team": "ORL", "year": "2012-13", "traditional": -2.4169926411846068, "advanced": -0.670942229568499}, {"name": "Raul Neto", "team": "UTA", "year": "2015-16", "traditional": -2.4312008604487865, "advanced": -1.9760773625388808}, {"name": "Nemanja Bjelica", "team": "MIN", "year": "2015-16", "traditional": -2.46293153902771, "advanced": -1.5971344818055528}, {"name": "Royce O'Neale", "team": "UTA", "year": "2017-18", "traditional": -2.4970653168018, "advanced": -1.613163900623034}, {"name": "Eric Maynor", "team": "TOT", "year": "2009-10", "traditional": -2.5246999028309975, "advanced": -2.371415051578217}, {"name": "Bruce Brown", "team": "DET", "year": "2018-19", "traditional": -2.5370973517886695, "advanced": -4.571380302922803}, {"name": "Kentavious Caldwell-Pope", "team": "DET", "year": "2013-14", "traditional": -2.585646757635166, "advanced": -2.6997345548222818}, {"name": "OG Anunoby", "team": "TOR", "year": "2017-18", "traditional": -2.610600091655593, "advanced": -0.9906626982819184}, {"name": "Norris Cole", "team": "MIA", "year": "2011-12", "traditional": -2.6229445008119785, "advanced": -3.9965580121439244}, {"name": "Chandler Hutchison", "team": "CHI", "year": "2018-19", "traditional": -2.6742682755515075, "advanced": -4.720219271807794}, {"name": "Brian Roberts", "team": "NOH", "year": "2012-13", "traditional": -2.7233495837121895, "advanced": 0.23718500053655678}, {"name": "Bojan Bogdanovic", "team": "BRK", "year": "2014-15", "traditional": -2.755368650105779, "advanced": -0.19488846100121787}, {"name": "Gary Neal", "team": "SAS", "year": "2010-11", "traditional": -2.7636491031452213, "advanced": 1.5303100626019415}, {"name": "Jeff Withey", "team": "NOP", "year": "2013-14", "traditional": -2.801363200254464, "advanced": -1.6320476977028022}, {"name": "JaKarr Sampson", "team": "PHI", "year": "2014-15", "traditional": -2.827607017625683, "advanced": -4.131279065165855}, {"name": "Dante Exum", "team": "UTA", "year": "2014-15", "traditional": -2.8326851139068996, "advanced": -5.204734406064566}, {"name": "Mario Hezonja", "team": "ORL", "year": "2015-16", "traditional": -2.8524773272890025, "advanced": -3.0794618892364656}, {"name": "Tim Hardaway", "team": "NYK", "year": "2013-14", "traditional": -2.8565180206300487, "advanced": 0.7332224434573851}, {"name": "Dorian Finney-Smith", "team": "DAL", "year": "2016-17", "traditional": -2.875140339893571, "advanced": -3.5593347697108357}, {"name": "Justin Jackson", "team": "SAC", "year": "2017-18", "traditional": -2.883325165480791, "advanced": -3.386269778901759}, {"name": "Zach Collins", "team": "POR", "year": "2017-18", "traditional": -2.91799241537587, "advanced": -4.657305603294073}, {"name": "Matthew Dellavedova", "team": "CLE", "year": "2013-14", "traditional": -2.927576859674763, "advanced": -2.6568488703660407}, {"name": "Malcolm Delaney", "team": "ATL", "year": "2016-17", "traditional": -3.008854736814581, "advanced": -5.251435656876902}, {"name": "Sindarius Thornwell", "team": "LAC", "year": "2017-18", "traditional": -3.0294265452247875, "advanced": -4.302247700482825}, {"name": "Terrence Ross", "team": "TOR", "year": "2012-13", "traditional": -3.043297002894632, "advanced": -2.332654850043994}, {"name": "Jaylen Brown", "team": "BOS", "year": "2016-17", "traditional": -3.102738935000807, "advanced": -2.8646008561851817}, {"name": "Jeffery Taylor", "team": "CHA", "year": "2012-13", "traditional": -3.1037001505767483, "advanced": -3.093962364746967}, {"name": "Trey Lyles", "team": "UTA", "year": "2015-16", "traditional": -3.1164932998062627, "advanced": -1.5498874514687986}, {"name": "Sam Young", "team": "MEM", "year": "2009-10", "traditional": -3.1282030368332947, "advanced": -1.5789266382503464}, {"name": "Landry Shamet", "team": "TOT", "year": "2018-19", "traditional": -3.1292829490912593, "advanced": -1.1201659512320525}, {"name": "Omer Asik", "team": "CHI", "year": "2010-11", "traditional": -3.150957129658118, "advanced": -2.3360230031637013}, {"name": "Alec Burks", "team": "UTA", "year": "2011-12", "traditional": -3.1608802825423754, "advanced": -0.2682154849700372}, {"name": "Nando De Colo", "team": "SAS", "year": "2012-13", "traditional": -3.2036972441667264, "advanced": -2.3082917716598703}, {"name": "Timothe Luwawu-Cabarrot", "team": "PHI", "year": "2016-17", "traditional": -3.2265266704063813, "advanced": -3.8321144142339083}, {"name": "James Ennis", "team": "MIA", "year": "2014-15", "traditional": -3.2415341472336223, "advanced": -2.0362500859764174}, {"name": "Jimmer Fredette", "team": "SAC", "year": "2011-12", "traditional": -3.2509574363968428, "advanced": -2.773956034343693}, {"name": "Draymond Green", "team": "GSW", "year": "2012-13", "traditional": -3.265065351779543, "advanced": -5.436474022430584}, {"name": "Juan Hernangomez", "team": "DEN", "year": "2016-17", "traditional": -3.3145315713339976, "advanced": -1.97858933428566}, {"name": "Enes Kanter", "team": "UTA", "year": "2011-12", "traditional": -3.360595758441761, "advanced": -2.6696262760944367}, {"name": "Gordon Hayward", "team": "UTA", "year": "2010-11", "traditional": -3.41705535437971, "advanced": -3.078664042538315}, {"name": "Mindaugas Kuzminskas", "team": "NYK", "year": "2016-17", "traditional": -3.53886773404507, "advanced": -1.9246161196353098}, {"name": "Wesley Iwundu", "team": "ORL", "year": "2017-18", "traditional": -3.764274239006305, "advanced": -5.446771194913881}, {"name": "Wayne Ellington", "team": "MIN", "year": "2009-10", "traditional": -3.884235411658985, "advanced": -4.026166649464085}, {"name": "Patrick McCaw", "team": "GSW", "year": "2016-17", "traditional": -3.9772025604136703, "advanced": -4.0602766061897055}, {"name": "Jeff Teague", "team": "ATL", "year": "2009-10", "traditional": -4.043063272411923, "advanced": -4.103472034883728}, {"name": "Will Barton", "team": "POR", "year": "2012-13", "traditional": -4.112414484572827, "advanced": -5.282526043846641}, {"name": "Alex Abrines", "team": "OKC", "year": "2016-17", "traditional": -4.11756494553037, "advanced": -2.7137826159567138}, {"name": "Frank Jackson", "team": "NOP", "year": "2018-19", "traditional": -4.120244489848389, "advanced": -5.0514002946224315}, {"name": "Davis Bertans", "team": "SAS", "year": "2016-17", "traditional": -4.147558099689465, "advanced": -0.4288647762646391}, {"name": "Malik Monk", "team": "CHO", "year": "2017-18", "traditional": -4.17219228572315, "advanced": -2.790556564968533}, {"name": "Tony Snell", "team": "CHI", "year": "2013-14", "traditional": -4.1756459730237605, "advanced": -3.9761924808352207}, {"name": "Semaj Christon", "team": "OKC", "year": "2016-17", "traditional": -4.208540146684724, "advanced": -7.703057065931594}, {"name": "Roko Ukic", "team": "TOR", "year": "2008-09", "traditional": -4.2862456398419075, "advanced": -4.64489726445284}, {"name": "Shelvin Mack", "team": "WAS", "year": "2011-12", "traditional": -4.289818023824542, "advanced": -3.847984218794476}, {"name": "Hamidou Diallo", "team": "OKC", "year": "2018-19", "traditional": -4.313776413358447, "advanced": -4.692888123891059}, {"name": "Greivis Vasquez", "team": "MEM", "year": "2010-11", "traditional": -4.410325271693326, "advanced": -4.981807531339565}, {"name": "Nik Stauskas", "team": "SAC", "year": "2014-15", "traditional": -4.703025757941927, "advanced": -5.374973619339991}, {"name": "Cedi Osman", "team": "CLE", "year": "2017-18", "traditional": -4.749097096099295, "advanced": -4.023818640813035}, {"name": "DeMarre Carroll", "team": "MEM", "year": "2009-10", "traditional": -4.819118532203838, "advanced": -5.688694943585713}, {"name": "Rashad Vaughn", "team": "MIL", "year": "2015-16", "traditional": -4.869040651567686, "advanced": -8.359771789421519}, {"name": "Kelly Oubre", "team": "WAS", "year": "2015-16", "traditional": -5.113256354839697, "advanced": -6.057455667065295}, {"name": "Semi Ojeleye", "team": "BOS", "year": "2017-18", "traditional": -5.2407624224508265, "advanced": -6.8378266613001575}, {"name": "Terrance Ferguson", "team": "OKC", "year": "2017-18", "traditional": -5.324164451781659, "advanced": -5.755118100071862}, {"name": "Brandon Paul", "team": "SAS", "year": "2017-18", "traditional": -5.421172049467147, "advanced": -6.0209128780285965}, {"name": "Damjan Rudez", "team": "IND", "year": "2014-15", "traditional": -5.477608138218958, "advanced": -4.207387574913942}]